LICENSE
README.rst
setup.py
ooquery/__init__.py
ooquery/expression.py
ooquery/ooquery.py
ooquery/operators.py
ooquery/parser.py
ooquery.egg-info/PKG-INFO
ooquery.egg-info/SOURCES.txt
ooquery.egg-info/dependency_links.txt
ooquery.egg-info/requires.txt
ooquery.egg-info/top_level.txt