Metadata-Version: 2.1
Name: ooquery
Version: 0.20.1
Summary: OpenObject Query Parser
Home-page: https://github.com/gisce/ooquery
Author: GISCE-TI, S.L.
Author-email: devel@gisce.net
License: MIT
Platform: UNKNOWN
License-File: LICENSE
